COPYING
MANIFEST.in
README.md
pyproject.toml
setup.py
docs/CHANGELOG.md
docs/FAQ.md
docs/README.md
docs/SECURITY.md
docs/SPONSORS.md
docs/Build/Debian.md
docs/Build/Dependencies.md
docs/Build/MSWindows.md
docs/Build/MacOS.md
docs/Build/Other.md
docs/Build/Packaging.md
docs/Build/README.md
docs/Build/RPM.md
docs/Build/Source.md
docs/Build/sonarqube-overview.png
docs/Build/subpackages.png
docs/Build/graphs/all.png
docs/Build/graphs/codecs.png
docs/Build/graphs/gtk3.png
docs/Build/graphs/packaging-tools.png
docs/Build/graphs/python3.png
docs/Build/graphs/tools.png
docs/Build/graphs/win32-deps.webp
docs/Features/Audio.md
docs/Features/Clipboard.md
docs/Features/DPI.md
docs/Features/Display.md
docs/Features/File-Transfers.md
docs/Features/Image-Depth.md
docs/Features/Keyboard-Shortcut-Window.png
docs/Features/Keyboard.md
docs/Features/Notifications.md
docs/Features/Printing.md
docs/Features/README.md
docs/Features/System-Tray.md
docs/Features/Webcam.md
docs/Network/AES.md
docs/Network/Encryption.md
docs/Network/Multicast-DNS.md
docs/Network/Protocol.md
docs/Network/QUIC.md
docs/Network/README.md
docs/Network/SSH.md
docs/Network/SSL.md
docs/Subsystems/Audio.md
docs/Subsystems/Bandwidth.md
docs/Subsystems/Clipboard.md
docs/Subsystems/Command.md
docs/Subsystems/Cursor.md
docs/Subsystems/Display.md
docs/Subsystems/Encoding.md
docs/Subsystems/Info.md
docs/Subsystems/Keyboard.md
docs/Subsystems/Logging.md
docs/Subsystems/MMAP.md
docs/Subsystems/Notification.md
docs/Subsystems/Ping.md
docs/Subsystems/Pointer.md
docs/Subsystems/Power.md
docs/Subsystems/README.md
docs/Subsystems/SSH_Agent.md
docs/Subsystems/Socket.md
docs/Subsystems/Tray.md
docs/Subsystems/Webcam.md
docs/Subsystems/Window.md
docs/Usage/Apache-Proxy.md
docs/Usage/Authentication.md
docs/Usage/Client-OpenGL.md
docs/Usage/Client.md
docs/Usage/Configuration.md
docs/Usage/Desktop.md
docs/Usage/Encodings.md
docs/Usage/Logging.md
docs/Usage/NVENC.md
docs/Usage/Nginx-Proxy.md
docs/Usage/OpenGL.md
xpra.egg-info/PKG-INFO
xpra.egg-info/SOURCES.txt
xpra.egg-info/dependency_links.txt
xpra.egg-info/requires.txt
xpra.egg-info/top_level.txt
