Metadata-Version: 2.1
Name: xpra
Version: 6.4.2
Summary: multi-platform screen and application forwarding system
Home-page: https://xpra.org/
Download-URL: https://xpra.org/src/
Author: Arthur Huillet
Author-email: Antoine Martin <antoine@xpra.org>, Nathaniel Smith <njs@pobox.com>
Maintainer-email: Antoine Martin <antoine@xpra.org>
License: 		    GNU GENERAL PUBLIC LICENSE
Project-URL: Homepage, https://xpra.org/
Project-URL: Source, https://github.com/Xpra-org/xpra
Project-URL: Funding, https://github.com/sponsors/totaam
Project-URL: Documentation, https://github.com/Xpra-org/xpra/docs
Keywords: remote
Classifier: Development Status :: 5 - Production/Stable
Classifier: Environment :: Console
Classifier: Environment :: X11 Applications :: GTK
Classifier: Intended Audience :: End Users/Desktop
Classifier: License :: OSI Approved :: GNU General Public License v2 or later (GPLv2+)
Classifier: Operating System :: Microsoft :: Windows
Classifier: Operating System :: POSIX
Classifier: Operating System :: MacOS :: MacOS X
Classifier: Programming Language :: Python
Classifier: Programming Language :: Python :: 3
Classifier: Programming Language :: Python :: 3.10
Classifier: Programming Language :: Python :: 3.11
Classifier: Programming Language :: Python :: 3.12
Requires-Python: >=3.10
License-File: COPYING
Provides-Extra: gui
Requires-Dist: pyopengl; extra == "gui"
Requires-Dist: pyopengl_accelerate; extra == "gui"
Provides-Extra: cli
Requires-Dist: paramiko; extra == "cli"
Requires-Dist: pyopenssl; extra == "cli"
Requires-Dist: cryptography; extra == "cli"
Requires-Dist: uvloop; extra == "cli"
Requires-Dist: aioquic; extra == "cli"
Requires-Dist: dbus; extra == "cli"
Requires-Dist: socks; extra == "cli"
Requires-Dist: pysocks; extra == "cli"
Requires-Dist: netifaces; extra == "cli"
Requires-Dist: dns; extra == "cli"
Requires-Dist: avahi; extra == "cli"
Requires-Dist: zeroconf; extra == "cli"
Requires-Dist: cups; extra == "cli"
Requires-Dist: psutil; extra == "cli"
Requires-Dist: cpuinfo; extra == "cli"
Requires-Dist: setproctitle; extra == "cli"
Requires-Dist: pyxdg; extra == "cli"
Requires-Dist: numpy; extra == "cli"
Requires-Dist: pycuda; extra == "cli"
Requires-Dist: pynvml; extra == "cli"
Requires-Dist: kerberos; extra == "cli"
Requires-Dist: gssapi; extra == "cli"
Requires-Dist: ldap3; extra == "cli"
Requires-Dist: ldap; extra == "cli"
Requires-Dist: oauthlib; extra == "cli"
Requires-Dist: pyu2f; extra == "cli"
